[
  {
    "ContainingType": "OnlineRideShareApi.Controllers.AccountController",
    "Method": "GetUsers",
    "RelativePath": "api/Account",
    "HttpMethod": "GET",
    "IsController": true,
    "Order": 0,
    "Parameters": [],
    "ReturnTypes": [
      {
        "Type": "System.Collections.Generic.IEnumerable\u00601[[OnlineRideShareApi.Dtos.UserDetailDto, OnlineRideShareApi, Version=1.0.0.0, Culture=neutral, PublicKeyToken=null]]",
        "MediaTypes": [
          "text/plain",
          "application/json",
          "text/json"
        ],
        "StatusCode": 200
      }
    ]
  },
  {
    "ContainingType": "OnlineRideShareApi.Controllers.AccountController",
    "Method": "ChangePassword",
    "RelativePath": "api/Account/change-password",
    "HttpMethod": "POST",
    "IsController": true,
    "Order": 0,
    "Parameters": [
      {
        "Name": "changePasswordDto",
        "Type": "OnlineRideShareApi.Dtos.ChangePasswordDto",
        "IsRequired": true
      }
    ],
    "ReturnTypes": []
  },
  {
    "ContainingType": "OnlineRideShareApi.Controllers.AccountController",
    "Method": "GetUserDetail",
    "RelativePath": "api/Account/detail",
    "HttpMethod": "GET",
    "IsController": true,
    "Order": 0,
    "Parameters": [],
    "ReturnTypes": [
      {
        "Type": "OnlineRideShareApi.Dtos.UserDetailDto",
        "MediaTypes": [
          "text/plain",
          "application/json",
          "text/json"
        ],
        "StatusCode": 200
      }
    ]
  },
  {
    "ContainingType": "OnlineRideShareApi.Controllers.AccountController",
    "Method": "ForgotPassowrd",
    "RelativePath": "api/Account/forgot-password",
    "HttpMethod": "POST",
    "IsController": true,
    "Order": 0,
    "Parameters": [
      {
        "Name": "forgotPasswordDto",
        "Type": "OnlineRideShareApi.Dtos.ForgotPasswordDto",
        "IsRequired": true
      }
    ],
    "ReturnTypes": []
  },
  {
    "ContainingType": "OnlineRideShareApi.Controllers.AccountController",
    "Method": "Login",
    "RelativePath": "api/Account/login",
    "HttpMethod": "POST",
    "IsController": true,
    "Order": 0,
    "Parameters": [
      {
        "Name": "loginDto",
        "Type": "OnlineRideShareApi.Dtos.LoginDto",
        "IsRequired": true
      }
    ],
    "ReturnTypes": [
      {
        "Type": "OnlineRideShareApi.Dtos.AuthResponseDto",
        "MediaTypes": [
          "text/plain",
          "application/json",
          "text/json"
        ],
        "StatusCode": 200
      }
    ]
  },
  {
    "ContainingType": "OnlineRideShareApi.Controllers.AccountController",
    "Method": "RefreshToken",
    "RelativePath": "api/Account/refresh-token",
    "HttpMethod": "POST",
    "IsController": true,
    "Order": 0,
    "Parameters": [
      {
        "Name": "tokenDto",
        "Type": "OnlineRideShareApi.Dtos.TokenDto",
        "IsRequired": true
      }
    ],
    "ReturnTypes": [
      {
        "Type": "OnlineRideShareApi.Dtos.AuthResponseDto",
        "MediaTypes": [
          "text/plain",
          "application/json",
          "text/json"
        ],
        "StatusCode": 200
      }
    ]
  },
  {
    "ContainingType": "OnlineRideShareApi.Controllers.AccountController",
    "Method": "Register",
    "RelativePath": "api/Account/register",
    "HttpMethod": "POST",
    "IsController": true,
    "Order": 0,
    "Parameters": [
      {
        "Name": "registerDto",
        "Type": "OnlineRideShareApi.Dtos.RegisterDto",
        "IsRequired": true
      }
    ],
    "ReturnTypes": [
      {
        "Type": "System.String",
        "MediaTypes": [
          "text/plain",
          "application/json",
          "text/json"
        ],
        "StatusCode": 200
      }
    ]
  },
  {
    "ContainingType": "OnlineRideShareApi.Controllers.AccountController",
    "Method": "ResetPassword",
    "RelativePath": "api/Account/reset-password",
    "HttpMethod": "POST",
    "IsController": true,
    "Order": 0,
    "Parameters": [
      {
        "Name": "resetPasswordDto",
        "Type": "OnlineRideShareApi.Dtos.ResetPasswordDto",
        "IsRequired": true
      }
    ],
    "ReturnTypes": []
  },
  {
    "ContainingType": "OnlineRideShareApi.Controllers.CompanyController",
    "Method": "GetCompany",
    "RelativePath": "api/Company",
    "HttpMethod": "GET",
    "IsController": true,
    "Order": 0,
    "Parameters": [],
    "ReturnTypes": [
      {
        "Type": "System.Collections.Generic.IEnumerable\u00601[[OnlineRideShareApi.Models.Company, OnlineRideShareApi, Version=1.0.0.0, Culture=neutral, PublicKeyToken=null]]",
        "MediaTypes": [
          "text/plain",
          "application/json",
          "text/json"
        ],
        "StatusCode": 200
      }
    ]
  },
  {
    "ContainingType": "OnlineRideShareApi.Controllers.CompanyController",
    "Method": "CreateCompany",
    "RelativePath": "api/Company",
    "HttpMethod": "POST",
    "IsController": true,
    "Order": 0,
    "Parameters": [
      {
        "Name": "company",
        "Type": "OnlineRideShareApi.Models.Company",
        "IsRequired": true
      }
    ],
    "ReturnTypes": []
  },
  {
    "ContainingType": "OnlineRideShareApi.Controllers.CompanyController",
    "Method": "Company",
    "RelativePath": "api/Company/{id}",
    "HttpMethod": "GET",
    "IsController": true,
    "Order": 0,
    "Parameters": [
      {
        "Name": "id",
        "Type": "System.Int32",
        "IsRequired": true
      }
    ],
    "ReturnTypes": [
      {
        "Type": "OnlineRideShareApi.Models.Company",
        "MediaTypes": [
          "text/plain",
          "application/json",
          "text/json"
        ],
        "StatusCode": 200
      }
    ]
  },
  {
    "ContainingType": "OnlineRideShareApi.Controllers.CompanyController",
    "Method": "DeleteCompany",
    "RelativePath": "api/Company/{id}",
    "HttpMethod": "DELETE",
    "IsController": true,
    "Order": 0,
    "Parameters": [
      {
        "Name": "id",
        "Type": "System.Int32",
        "IsRequired": true
      }
    ],
    "ReturnTypes": [
      {
        "Type": "OnlineRideShareApi.Models.Company",
        "MediaTypes": [
          "text/plain",
          "application/json",
          "text/json"
        ],
        "StatusCode": 200
      }
    ]
  },
  {
    "ContainingType": "OnlineRideShareApi.Controllers.CompanyController",
    "Method": "EditCompany",
    "RelativePath": "api/Company/{id}",
    "HttpMethod": "PUT",
    "IsController": true,
    "Order": 0,
    "Parameters": [
      {
        "Name": "id",
        "Type": "System.Int32",
        "IsRequired": true
      },
      {
        "Name": "company",
        "Type": "OnlineRideShareApi.Models.Company",
        "IsRequired": true
      }
    ],
    "ReturnTypes": []
  },
  {
    "ContainingType": "OnlineRideShareApi.Controllers.RolesController",
    "Method": "CreateRole",
    "RelativePath": "api/Roles",
    "HttpMethod": "POST",
    "IsController": true,
    "Order": 0,
    "Parameters": [
      {
        "Name": "createRoleDto",
        "Type": "OnlineRideShareApi.Dtos.CreateRoleDto",
        "IsRequired": true
      }
    ],
    "ReturnTypes": []
  },
  {
    "ContainingType": "OnlineRideShareApi.Controllers.RolesController",
    "Method": "GetRoles",
    "RelativePath": "api/Roles",
    "HttpMethod": "GET",
    "IsController": true,
    "Order": 0,
    "Parameters": [],
    "ReturnTypes": [
      {
        "Type": "System.Collections.Generic.IEnumerable\u00601[[OnlineRideShareApi.Dtos.RoleResponseDto, OnlineRideShareApi, Version=1.0.0.0, Culture=neutral, PublicKeyToken=null]]",
        "MediaTypes": [
          "text/plain",
          "application/json",
          "text/json"
        ],
        "StatusCode": 200
      }
    ]
  },
  {
    "ContainingType": "OnlineRideShareApi.Controllers.RolesController",
    "Method": "DeleteRole",
    "RelativePath": "api/Roles/{id}",
    "HttpMethod": "DELETE",
    "IsController": true,
    "Order": 0,
    "Parameters": [
      {
        "Name": "id",
        "Type": "System.String",
        "IsRequired": true
      }
    ],
    "ReturnTypes": []
  },
  {
    "ContainingType": "OnlineRideShareApi.Controllers.RolesController",
    "Method": "AssignRole",
    "RelativePath": "api/Roles/assign",
    "HttpMethod": "POST",
    "IsController": true,
    "Order": 0,
    "Parameters": [
      {
        "Name": "roleAssignDto",
        "Type": "OnlineRideShareApi.Dtos.RoleAssignDto",
        "IsRequired": true
      }
    ],
    "ReturnTypes": []
  },
  {
    "ContainingType": "API.Controllers.WeatherForecastController",
    "Method": "Get",
    "RelativePath": "WeatherForecast",
    "HttpMethod": "GET",
    "IsController": true,
    "Order": 0,
    "Parameters": [],
    "ReturnTypes": [
      {
        "Type": "System.Collections.Generic.IEnumerable\u00601[[OnlineRideShareApi.WeatherForecast, OnlineRideShareApi, Version=1.0.0.0, Culture=neutral, PublicKeyToken=null]]",
        "MediaTypes": [
          "text/plain",
          "application/json",
          "text/json"
        ],
        "StatusCode": 200
      }
    ],
    "EndpointName": "GetWeatherForecast"
  }
]